{
    "plugins": [
        "etoc",
        "styles-sass",
        "customtheme",
        "-highlight",
        "sunlight-highlighter",
        "quiz",
        "collapsible-chapters",
        "back-to-top-button" 
    ],
    "styles": {
        "pdf": "styles/pdf.sass",
        "website": "styles/website.css"
    },
    "pluginsConfig": {
        "etoc": {
            "mindepth": 2,
            "maxdepth": 4,
            "notoc": false
        },
        "customtheme": {
            "css": [
                "styles/website.css"
            ]
        },
        "theme-default": {
            "showLevel": true
        },
        "quiz": {
            "labels": {
                "check"             : "Verificar resposta",
                "showExplanation"   : "Explain", 
                "showCorrect"       : "Solució",   
                "explanationHeader" : "Explanation"
            },
            "text": {
                "noChosen"    : "Tria com a mínim una resposta",  
                "incomplete"  : "Some correct answers are missing" 
            },
            "buttons": {
                "showCorrect"       : true, 
                "showExplanation"   : true 
            }
        },
        "collapsible-chapters":{}
    },
    "title": "Sistemes Operatius en Xarxa",
    "author": "Sergi Coll",
    "language": "es"
}